[
  {
    "SiteTitle": "tilgjengelighet",
    "ProjectName": "Tilgjengelighet_title",
    "HeaderIcon": "wheelchair",
    "HeaderTitle": "tilgjengelighet"
  },
  {
    "SiteTitle": "fastmerker",
    "ProjectName": "Fastmerker_title",
    "HeaderIcon": "map-pin",
    "HeaderTitle": "fastmerker"
  },
  {
    "SiteTitle": "nrl",
    "ProjectName": "nrl",
    "HeaderIcon": "plane",
    "HeaderTitle": "nrl"
  },
  {
    "SiteTitle": "norgeskart",
    "ProjectName": "norgeskart",
    "HeaderIcon": "home",
    "HeaderTitle": "norgeskart"
  },
  {
    "SiteTitle": "ssr",
    "ProjectName": "ssr",
    "HeaderIcon": "map-signs",
    "HeaderTitle": "ssr"
  },
  {
    "SiteTitle": "dekning",
    "ProjectName": "Dekning_title",
    "HeaderIcon": "map",
    "HeaderTitle": "dekning"
  },
  {
    "SiteTitle": "vectortilesdemo",
    "ProjectName": "vectortilesdemo",
    "HeaderIcon": "map",
    "HeaderTitle": "vectortilesdemo"
  }
]
